setup.py
gasflow/__init__.py
gasflow/gas_pipe.py
gasflow/state_equation.py
gasflow/util.py
gasflow.egg-info/PKG-INFO
gasflow.egg-info/SOURCES.txt
gasflow.egg-info/dependency_links.txt
gasflow.egg-info/requires.txt
gasflow.egg-info/top_level.txt